LICENSE
MANIFEST.in
README.md
pyproject.toml
setup.py
lazycon/__init__.py
lazycon/__version__.py
lazycon/console.py
lazycon/exceptions.py
lazycon/main.py
lazycon/parser.py
lazycon/py.typed
lazycon/render.py
lazycon/scope.py
lazycon/statements.py
lazycon/thunk.py
lazycon/visitor.py
lazycon.egg-info/PKG-INFO
lazycon.egg-info/SOURCES.txt
lazycon.egg-info/dependency_links.txt
lazycon.egg-info/entry_points.txt
lazycon.egg-info/top_level.txt
lazycon/semantics/__init__.py
lazycon/semantics/analyzer.py
lazycon/semantics/locals.py
lazycon/semantics/visitor.py
tests/test_engine.py
tests/test_parser.py
tests/test_semantics.py