Metadata-Version: 2.1
Name: lazycon
Version: 0.6.4
Summary: Easy config files in pure Python
Home-page: https://github.com/maxme1/lazycon
Download-URL: https://github.com/maxme1/lazycon/archive/v0.6.4.tar.gz
Author: Max
Author-email: Max <max@ira-labs.com>
License: MIT License
Project-URL: Homepage, https://github.com/maxme1/lazycon
Project-URL: Bug Tracker, https://github.com/maxme1/lazycon/issues
Project-URL: Source, https://github.com/maxme1/lazycon
Keywords: config,lazy,interpreter
Classifier: Development Status :: 5 - Production/Stable
Classifier: License :: OSI Approved :: MIT License
Classifier: Programming Language :: Python :: 3
Classifier: Programming Language :: Python :: 3.6
Classifier: Programming Language :: Python :: 3.7
Classifier: Programming Language :: Python :: 3.8
Classifier: Programming Language :: Python :: 3.9
Classifier: Programming Language :: Python :: 3.10
Classifier: Programming Language :: Python :: 3.11
Classifier: Programming Language :: Python :: 3 :: Only
Requires-Python: >=3.6
License-File: LICENSE
